audioptic.py
audioptic-1.0.1.dist-info/METADATA
audioptic-1.0.1.dist-info/WHEEL
audioptic-1.0.1.dist-info/entry_points.txt
audioptic-1.0.1.dist-info/licenses/LICENSE
audioptic-1.0.1.dist-info/RECORD
