Metadata-Version: 2.4
Name: audioptic
Version: 1.0.1
Summary: Bidirectional spectrogram-based audio-image converter
Author-email: Thomas Xin <thomasxin@gmail.com>
License: MIT
License-File: LICENSE
Classifier: Programming Language :: Python :: 3
Requires-Python: >=3.8
Requires-Dist: imageio-ffmpeg>=0.6.0
Requires-Dist: numpy>=2.2.6
Requires-Dist: opencv-python>=4.12.0.88
Requires-Dist: streamshatter>=1.0.11
